crosswork_companion/__init__.py
crosswork_companion/crosswork_companion.py
crosswork_companion/crosswork_companion_csv.j2
crosswork_companion/crosswork_companion_html.j2
crosswork_companion/crosswork_companion_markdown.j2
crosswork_companion/crosswork_companion_mindmap.j2
crosswork_companion/datatable_footer.j2
crosswork_companion/datatable_header.j2
crosswork_companion/script.py
crosswork_companion-0.1.1.dist-info/METADATA
crosswork_companion-0.1.1.dist-info/WHEEL
crosswork_companion-0.1.1.dist-info/LICENSE
crosswork_companion-0.1.1.dist-info/entry_points.txt
crosswork_companion-0.1.1.dist-info/RECORD
