Metadata-Version: 2.1
Name: crosswork-companion
Version: 0.1.1
Summary: Business ready documents from Cisco Crosswork
Author: John Capobianco
Author-email: ptcapo@gmail.com
Requires-Python: >=3.10,<4.0
Classifier: Programming Language :: Python :: 3
Classifier: Programming Language :: Python :: 3.10
Classifier: Programming Language :: Python :: 3.11
Requires-Dist: aiofiles (>=22.1.0,<23.0.0)
Requires-Dist: aiohttp (>=3.8.3,<4.0.0)
Requires-Dist: jinja2 (>=3.1.2,<4.0.0)
Requires-Dist: pyyaml (>=6.0,<7.0)
Requires-Dist: requests (>=2.28.2,<3.0.0)
Requires-Dist: rich-click (>=1.6.1,<2.0.0)
